galerkin_transformer/__init__.py
galerkin_transformer/ft.py
galerkin_transformer/layers.py
galerkin_transformer/model.py
galerkin_transformer/ns_lite.py
galerkin_transformer/utils.py
galerkin_transformer/utils_ft.py
galerkin_transformer/data/__init__.py
galerkin_transformer/examples/__init__.py
galerkin_transformer/examples/encoder_memory_profile.py
galerkin_transformer/examples/ex1_burgers.py
galerkin_transformer/examples/ex1_burgers_random_fourier_features.py
galerkin_transformer/examples/ex1_burgers_super_res.py
galerkin_transformer/examples/ex1_memory_profile.py
galerkin_transformer/examples/ex2_darcy.py
galerkin_transformer/examples/ex2_memory_profile.py
galerkin_transformer/examples/ex3_darcy_inv.py
galerkin_transformer/examples/ex3_memory_profile.py
galerkin_transformer/examples/ex4_navier_stokes_2+1d.py
galerkin_transformer/examples/libs_path.py
galerkin_transformer-0.2.1.dist-info/LICENSE
galerkin_transformer-0.2.1.dist-info/METADATA
galerkin_transformer-0.2.1.dist-info/WHEEL
galerkin_transformer-0.2.1.dist-info/top_level.txt
galerkin_transformer-0.2.1.dist-info/RECORD
