Metadata-Version: 2.1
Name: galerkin-transformer
Version: 0.2.1
Summary: Galerkin Transformer
Home-page: https://github.com/scaomath/galerkin-transformer
Author: Shuhao Cao
Author-email: scao.math@gmail.com
License: MIT
Keywords: transformers,attention,galerkin,hilbert,pde
Classifier: Development Status :: 4 - Beta
Classifier: Intended Audience :: Science/Research
Classifier: Topic :: Scientific/Engineering :: Mathematics
Classifier: License :: OSI Approved :: MIT License
Classifier: Programming Language :: Python :: 3.8
License-File: LICENSE
Requires-Dist: seaborn
Requires-Dist: torchinfo
Requires-Dist: numpy
Requires-Dist: torch (>=1.9.0)
Requires-Dist: plotly
Requires-Dist: scipy
Requires-Dist: psutil
Requires-Dist: matplotlib
Requires-Dist: tqdm
Requires-Dist: PyYAML
